LICENSE
README.rst
setup.cfg
setup.py
py_kucoin_extra/__init__.py
py_kucoin_extra/client.py
py_kucoin_extra/exceptions.py
py_kucoin_extra/utils.py
py_kucoin_extra.egg-info/PKG-INFO
py_kucoin_extra.egg-info/SOURCES.txt
py_kucoin_extra.egg-info/dependency_links.txt
py_kucoin_extra.egg-info/requires.txt
py_kucoin_extra.egg-info/top_level.txt
py_kucoin_extra/asyncio/__init__.py
py_kucoin_extra/asyncio/websockets.py