Metadata-Version: 2.1
Name: py-kucoin-extra
Version: 1.2.1
Summary: Kucoin REST API v2 python implementation
Home-page: https://github.com/javadebadi/python-kucoin
Author: Javad Ebadi
Author-email: javad.ebadi.1990@gmail.com
License: MIT
Platform: UNKNOWN
Requires-Python: >=3.7
License-File: LICENSE
